scavager/__init__.py
scavager/main.py
scavager/scav2diffacto.py
scavager/scav2nsaf.py
scavager/search.py
scavager/utils.py
scavager/utils_figures.py
scavager-0.2.17.dist-info/licenses/LICENSE
scavager-0.2.17.dist-info/METADATA
scavager-0.2.17.dist-info/WHEEL
scavager-0.2.17.dist-info/entry_points.txt
scavager-0.2.17.dist-info/top_level.txt
scavager-0.2.17.dist-info/RECORD
