Metadata-Version: 2.4
Name: scavager
Version: 0.2.17
Summary: Proteomics post-search algorithm
Author: Julia Bubis
Author-email: Mark Ivanov <markmipt@gmail.com>, Lev Levitsky <lev.levitsky@phystech.edu>
License-Expression: Apache-2.0
Project-URL: Homepage, https://github.com/markmipt/scavager
Project-URL: Issues, https://github.com/markmipt/scavager/issues
Classifier: Programming Language :: Python :: 3
Classifier: Operating System :: OS Independent
Classifier: Topic :: Scientific/Engineering :: Bio-Informatics
Classifier: Intended Audience :: Science/Research
Requires-Python: >=3.9
License-File: LICENSE
Requires-Dist: numpy
Requires-Dist: scipy
Requires-Dist: pandas
Requires-Dist: pyteomics>=3.5
Requires-Dist: lxml
Requires-Dist: catboost
Requires-Dist: scikit-learn
Requires-Dist: matplotlib
Dynamic: license-file
